drf_response_wrapper/__init__.py
drf_response_wrapper/middleware.py
drf_response_wrapper/version.py
drf_response_wrapper-1.2.5.dist-info/METADATA
drf_response_wrapper-1.2.5.dist-info/WHEEL
drf_response_wrapper-1.2.5.dist-info/top_level.txt
drf_response_wrapper-1.2.5.dist-info/RECORD
