Metadata-Version: 2.4
Name: drf_response_wrapper
Version: 1.2.5
Summary: DRF middleware to wrap all API responses
Home-page: https://github.com/yourusername/drf-response-wrapper
Author: Md Harun Or Roshed Riyad
Author-email: rieadhasan499@gmail.com
Classifier: Programming Language :: Python :: 3
Classifier: Framework :: Django
Classifier: License :: OSI Approved :: MIT License
Requires-Python: >=3.8
Dynamic: author
Dynamic: author-email
Dynamic: classifier
Dynamic: description
Dynamic: description-content-type
Dynamic: home-page
Dynamic: requires-python
Dynamic: summary
